[
  {
    "id":101,
    "questionId":1715275777620000,
    "question":"What is yiour gender?",
    "questionType":"radio",
    "isMandatory":false,
    "image":"https://img.freepik.com/free-vector/one-happy-boy-eating-table_1308-68783.jpg?w=740&t=st=1711106859~exp=1711107459~hmac=2afd13dc2fed656de8d90fffb61d47b9e5995fded340798d555f2ced1a929acd",
    "imageHeight":120,
    "imageWidth":120,
    "inputType":"Text",
    "description":"zjfhbvldhfblkdhfb",
    "answerChoices":{
      "male":[
        {
          "id":202,
          "questionId":1715275890533000,
          "question":"Do you ahve smoking habit?",
          "questionType":"list",
          "isMandatory":false,
          "image":"https://img.freepik.com/free-vector/one-happy-boy-eating-table_1308-68783.jpg?w=740&t=st=1711106859~exp=1711107459~hmac=2afd13dc2fed656de8d90fffb61d47b9e5995fded340798d555f2ced1a929acd",
          "imageHeight":120,
          "imageWidth":120,
          "score":24,
          "inputType":"Text",
          "description":"shgrblkasglhvbeasgn,r",
          "answerChoices":{
            "yes":[
              {
                "id":303,
                "questionId":1715275927827000,
                "question":"Then what about the drinking habit?",
                "questionType":"list",
                "isMandatory":false,
                "image":null,
                "imageHeight":0,
                "imageWidth":0,
                "score":13,
                "inputType":"",
                "description":"",
                "answerChoices":{
                  "yes":[

                  ],
                  "no":[

                  ]
                }
              }
            ],
            "no":[

            ]
          }
        }
      ],
      "female":[
        {
          "id":505,
          "questionId":1715275968040000,
          "question":"Are you pregnant?",
          "questionType":"list",
          "isMandatory":true,
          "image":"https://img.freepik.com/free-vector/one-happy-boy-eating-table_1308-68783.jpg?w=740&t=st=1711106859~exp=1711107459~hmac=2afd13dc2fed656de8d90fffb61d47b9e5995fded340798d555f2ced1a929acd",
          "imageHeight":120,
          "imageWidth":120,
          "score":18,
          "inputType":"Text",
          "description":"",
          "answerChoices":{
            "yes":[
              {
                "id":606,
                "questionId":1715276019090000,
                "question":"Are you taking the medication.",
                "questionType":"radio",
                "isMandatory":false,
                "image":"https://img.freepik.com/free-vector/one-happy-boy-eating-table_1308-68783.jpg?w=740&t=st=1711106859~exp=1711107459~hmac=2afd13dc2fed656de8d90fffb61d47b9e5995fded340798d555f2ced1a929acd",
                "imageHeight":100,
                "imageWidth":100,
                "score":25,
                "inputType":"Text",
                "description":"",
                "answerChoices":{
                  "yes":[

                  ],
                  "no":[

                  ]
                }
              }
            ],
            "no":[

            ]
          }
        }
      ],
      "other":[

      ]
    }
  },
  {
    "id":707,
    "questionId":1715276067785000,
    "question":"How many languages do you ?",
    "questionType":"multiplechoices",
    "isMandatory":false,
    "image":"https://img.freepik.com/free-vector/one-happy-boy-eating-table_1308-68783.jpg?w=740&t=st=1711106859~exp=1711107459~hmac=2afd13dc2fed656de8d90fffb61d47b9e5995fded340798d555f2ced1a929acd",
    "imageHeight":120,
    "imageWidth":120,
    "inputType":"Text",
    "description":null,
    "answerChoices":{
      "Telugu":[

      ],
      "hindi":[

      ],
      "english":[

      ],
      "spanish":[

      ]
    }
  },
  {
    "id":808,
    "questionId":1715276068160000,
    "question":"Which item do have?",
    "questionType":"drop_down",
    "isMandatory":false,
    "image":"https://img.freepik.com/free-vector/one-happy-boy-eating-table_1308-68783.jpg?w=740&t=st=1711106859~exp=1711107459~hmac=2afd13dc2fed656de8d90fffb61d47b9e5995fded340798d555f2ced1a929acd",
    "imageHeight":120,
    "imageWidth":120,
    "inputType":"Text",
    "description":null,
    "answerChoices":{
      "milk":[

      ],
      "curd":[

      ],
      "butter":[

      ],
      "butter_milk":[

      ]
    }
  },
  {
    "id":909,
    "questionId":1715276069519000,
    "question":"Types of non-veg that you had lunch",
    "questionType":"radio",
    "isMandatory":false,
    "image":"https://img.freepik.com/free-vector/one-happy-boy-eating-table_1308-68783.jpg?w=740&t=st=1711106859~exp=1711107459~hmac=2afd13dc2fed656de8d90fffb61d47b9e5995fded340798d555f2ced1a929acd",
    "imageHeight":120,
    "imageWidth":120,
    "inputType":"Text",
    "description":null,
    "answerChoices":{
      "chicken":[
        {
          "id":110,
          "questionId":1715276280781000,
          "question":"Which chicken type do you want?",
          "questionType":"list",
          "isMandatory":false,
          "image":null,
          "imageHeight":0,
          "imageWidth":0,
          "score":30,
          "inputType":"Text",
          "description":"agvdkcasgvEFjlhS dv",
          "answerChoices":{
            "fry":[

            ],
            "grewi(pulusu)":[

            ]
          }
        }
      ],
      "mutton":[

      ],
      "fish":[

      ]
    }
  },
  {
    "id":120,
    "questionId":1715276384310000,
    "question":"How fluent are you in english",
    "questionType":"slider",
    "isMandatory":true,
    "image":"https://img.freepik.com/free-vector/one-happy-boy-eating-table_1308-68783.jpg?w=740&t=st=1711106859~exp=1711107459~hmac=2afd13dc2fed656de8d90fffb61d47b9e5995fded340798d555f2ced1a929acd",
    "imageHeight":120,
    "imageWidth":120,
    "inputType":null,
    "description":null,
    "answerChoices":null
  },
  {
    "id":130,
    "questionId":1715276385753000,
    "question":"How you are going to home tonight through?",
    "questionType":"search_item",
    "isMandatory":false,
    "image":"",
    "imageHeight":0,
    "imageWidth":0,
    "inputType":null,
    "description":null,
    "answerChoices":{
      "bus":[

      ],
      "train":[

      ],
      "van":null
    }
  },
  {
    "id":1000,
    "questionId":1715276063756,
    "question":"Types of non that you had for dinner",
    "questionType":"radio",
    "isMandatory":false,
    "image":"https://img.freepik.com/free-vector/one-happy-boy-eating-table_1308-68783.jpg?w=740&t=st=1711106859~exp=1711107459~hmac=2afd13dc2fed656de8d90fffb61d47b9e5995fded340798d555f2ced1a929acd",
    "imageHeight":120,
    "imageWidth":120,
    "inputType":"Text",
    "description":null,
    "answerChoices":{
      "green-leaf":[
        {
          "id":1107,
          "questionId":17152762807567,
          "question":"Which green type do you want?",
          "questionType":"list",
          "isMandatory":false,
          "image":null,
          "imageHeight":0,
          "imageWidth":0,
          "score":30,
          "inputType":"Text",
          "description":"agvdkcasgvEFjlhS dv",
          "answerChoices":{
            "gongura":[

            ],
            "palakura":[

            ]
          }
        }
      ],
      "Dal":[
        {}
      ],
      "Veg-rice":[
        {}
      ]
    }
  }
]